quarks2_fractal/__init__.py
quarks2_fractal/__version__.py
quarks2_fractal/base/__init__.py
quarks2_fractal/base/encoder_decoder.py
quarks2_fractal/base/model.py
quarks2_fractal/classifier/__init__.py
quarks2_fractal/classifier/cls_decoder.py
quarks2_fractal/classifier/model.py
quarks2_fractal/classifier/remap.py
quarks2_fractal/common/__init__.py
quarks2_fractal/common/blocks.py
quarks2_fractal/datasets/__init__.py
quarks2_fractal/datasets/agu.py
quarks2_fractal/datasets/cls_labels.py
quarks2_fractal/datasets/dataloader.py
quarks2_fractal/datasets/datasets.py
quarks2_fractal/datasets/helper.py
quarks2_fractal/datasets/seversteal.py
quarks2_fractal/encoders/__init__.py
quarks2_fractal/encoders/_preprocessing.py
quarks2_fractal/encoders/densenet.py
quarks2_fractal/encoders/dpn.py
quarks2_fractal/encoders/efficientnet.py
quarks2_fractal/encoders/inceptionresnetv2.py
quarks2_fractal/encoders/resnet.py
quarks2_fractal/encoders/senet.py
quarks2_fractal/encoders/vgg.py
quarks2_fractal/engine/__init__.py
quarks2_fractal/engine/infer.py
quarks2_fractal/engine/trainer.py
quarks2_fractal/engine/utils.py
quarks2_fractal/fpn/__init__.py
quarks2_fractal/fpn/decoder.py
quarks2_fractal/fpn/model.py
quarks2_fractal/linknet/__init__.py
quarks2_fractal/linknet/decoder.py
quarks2_fractal/linknet/model.py
quarks2_fractal/pretrainedmodels/__init__.py
quarks2_fractal/pretrainedmodels/datasets/__init__.py
quarks2_fractal/pretrainedmodels/datasets/utils.py
quarks2_fractal/pretrainedmodels/datasets/voc.py
quarks2_fractal/pretrainedmodels/models/__init__.py
quarks2_fractal/pretrainedmodels/models/bninception.py
quarks2_fractal/pretrainedmodels/models/cafferesnet.py
quarks2_fractal/pretrainedmodels/models/dpn.py
quarks2_fractal/pretrainedmodels/models/fbresnet/resnet152_dump.lua
quarks2_fractal/pretrainedmodels/models/fbresnet/resnet152_load.py
quarks2_fractal/pretrainedmodels/models/fbresnet.py
quarks2_fractal/pretrainedmodels/models/inceptionresnetv2.py
quarks2_fractal-0.1.5.dist-info/entry_points.txt
quarks2_fractal-0.1.5.dist-info/WHEEL
quarks2_fractal-0.1.5.dist-info/METADATA
quarks2_fractal-0.1.5.dist-info/RECORD
