Metadata-Version: 2.1
Name: quarks2-fractal
Version: 0.1.5
Summary: Integrated image classification and semantic segmentation package
License: Apache-2.0
Author: PrakashJay
Author-email: vanapalli.prakash@fractal.ai
Requires-Python: ==3.6.9
Classifier: License :: OSI Approved :: Apache Software License
Classifier: Programming Language :: Python :: 3
Requires-Dist: EasyDict (>=1.9,<2.0)
Requires-Dist: albumentations (>=0.4.1,<0.5.0)
Requires-Dist: captum (>=0.1.0,<0.2.0)
Requires-Dist: click (>=7.0,<8.0)
Requires-Dist: efficientnet_pytorch (==0.5.1)
Requires-Dist: hyperdash (>=0.15.3,<0.16.0)
Requires-Dist: ipykernel (>=5.1,<6.0)
Requires-Dist: ipython (>=7.8,<8.0)
Requires-Dist: loguru (>=0.3.2,<0.4.0)
Requires-Dist: opencv-python (>=4.1,<5.0)
Requires-Dist: pandas (>=0.25.2,<0.26.0)
Requires-Dist: pretrainedmodels (>=0.7.4,<0.8.0)
Requires-Dist: scikit-learn (>=0.21.3,<0.22.0)
Requires-Dist: torch (==1.3.0)
Requires-Dist: torchnet (>=0.0.4,<0.0.5)
Requires-Dist: torchvision (==0.4.1)
